mufidecode.py
mufidecode-0.1.0.dist-info/LICENSE
mufidecode-0.1.0.dist-info/METADATA
mufidecode-0.1.0.dist-info/WHEEL
mufidecode-0.1.0.dist-info/top_level.txt
mufidecode-0.1.0.dist-info/RECORD
