Metadata-Version: 2.1
Name: mufidecode
Version: 0.1.0
Summary: Unidecode with medieval flavor
Home-page: https://github.com/ponteineptique/mufidecode
Author: Thibault Clérice
License: GPL
Platform: UNKNOWN
Classifier: License :: OSI Approved :: MIT License
Classifier: Programming Language :: Python
Classifier: Programming Language :: Python :: 3
Requires-Python: >=3.4.0
Requires-Dist: unidecode
